{
  "settings": {
    "enabled": true,
    "background": "#050B10",
    "text_color": "#ffffff",
    "accent_color": "#5EEAD4"
  },
  "content": {
    "title": "A MI TÖRTÉNETÜNK",
    "subtitle": "Hogyan jutottunk el idáig",
    "steps": [
      {
        "year": "2020",
        "title": "A Kezdetek",
        "description": "Elindultunk egy kis garázsból, de nagy álmokkal.",
        "image": ""
      },
      {
        "year": "2022",
        "title": "Növekedés",
        "description": "Bővült a csapat és új piacokra léptünk.",
        "image": ""
      },
      {
        "year": "2024",
        "title": "Jelen",
        "description": "Piacvezető megoldásokkal segítjük ügyfeleinket.",
        "image": ""
      }
    ]
  }
}